g4f7/__init__.py
g4f7/cli.py
g4f7/debug.py
g4f7/errors.py
g4f7/models.py
g4f7/requests.py
g4f7/typing.py
g4f7/webdriver.py
g4f7/Provider/AItianhu.py
g4f7/Provider/AItianhuSpace.py
g4f7/Provider/AiAsk.py
g4f7/Provider/AiChatOnline.py
g4f7/Provider/Aichat.py
g4f7/Provider/Berlin.py
g4f7/Provider/Bing.py
g4f7/Provider/ChatAnywhere.py
g4f7/Provider/ChatBase.py
g4f7/Provider/ChatForAi.py
g4f7/Provider/Chatgpt4Online.py
g4f7/Provider/ChatgptAi.py
g4f7/Provider/ChatgptDemo.py
g4f7/Provider/ChatgptDemoAi.py
g4f7/Provider/ChatgptFree.py
g4f7/Provider/ChatgptLogin.py
g4f7/Provider/ChatgptNext.py
g4f7/Provider/ChatgptX.py
g4f7/Provider/DeepInfra.py
g4f7/Provider/FakeGpt.py
g4f7/Provider/FreeGpt.py
g4f7/Provider/GPTalk.py
g4f7/Provider/GeekGpt.py
g4f7/Provider/GptChatly.py
g4f7/Provider/GptForLove.py
g4f7/Provider/GptGo.py
g4f7/Provider/GptGod.py
g4f7/Provider/GptTalkRu.py
g4f7/Provider/Hashnode.py
g4f7/Provider/Koala.py
g4f7/Provider/Liaobots.py
g4f7/Provider/Llama2.py
g4f7/Provider/MyShell.py
g4f7/Provider/OnlineGpt.py
g4f7/Provider/Opchatgpts.py
g4f7/Provider/PerplexityAi.py
g4f7/Provider/Phind.py
g4f7/Provider/Pi.py
g4f7/Provider/TalkAi.py
g4f7/Provider/Vercel.py
g4f7/Provider/Ylokh.py
g4f7/Provider/You.py
g4f7/Provider/Yqcloud.py
g4f7/Provider/__init__.py
g4f7/Provider/base_provider.py
g4f7/Provider/helper.py
g4f7/Provider/retry_provider.py
g4f7/Provider/deprecated/Acytoo.py
g4f7/Provider/deprecated/AiService.py
g4f7/Provider/deprecated/Aibn.py
g4f7/Provider/deprecated/Ails.py
g4f7/Provider/deprecated/Aivvm.py
g4f7/Provider/deprecated/ChatgptDuo.py
g4f7/Provider/deprecated/CodeLinkAva.py
g4f7/Provider/deprecated/Cromicle.py
g4f7/Provider/deprecated/DfeHub.py
g4f7/Provider/deprecated/EasyChat.py
g4f7/Provider/deprecated/Equing.py
g4f7/Provider/deprecated/FastGpt.py
g4f7/Provider/deprecated/Forefront.py
g4f7/Provider/deprecated/GetGpt.py
g4f7/Provider/deprecated/H2o.py
g4f7/Provider/deprecated/Lockchat.py
g4f7/Provider/deprecated/Myshell.py
g4f7-0.1.9.5.dist-info/LICENSE
g4f7-0.1.9.5.dist-info/METADATA
g4f7-0.1.9.5.dist-info/WHEEL
g4f7-0.1.9.5.dist-info/entry_points.txt
g4f7-0.1.9.5.dist-info/top_level.txt
g4f7-0.1.9.5.dist-info/RECORD
