Metadata-Version: 2.1
Name: g4f7
Version: 0.1.9.5
Summary: [Fork] The official gpt4free repository | various collection of powerful language models
Home-page: https://github.com/xtekky/gpt4free
Author: Tekky
Author-email: <support@g4f7.ai>
Project-URL: Source Code, https://github.com/xtekky/gpt4free
Project-URL: Bug Tracker, https://github.com/xtekky/gpt4free/issues
Keywords: python,chatbot,reverse-engineering,openai,chatbots,gpt,language-model,gpt-3,gpt3,openai-api,gpt-4,gpt4,chatgpt,chatgpt-api,openai-chatgpt,chatgpt-free,chatgpt-4,chatgpt4,chatgpt4-api,free,free-gpt,gpt4free,g4f
Classifier: Development Status :: 2 - Pre-Alpha
Classifier: Intended Audience :: Developers
Classifier: Programming Language :: Python :: 3
Classifier: Operating System :: Unix
Classifier: Operating System :: MacOS :: MacOS X
Classifier: Operating System :: Microsoft :: Windows
License-File: LICENSE
Requires-Dist: requests
Requires-Dist: pycryptodome
Requires-Dist: curl-cffi >=0.5.10b4
Requires-Dist: aiohttp
Requires-Dist: certifi
Requires-Dist: browser-cookie3
Requires-Dist: websockets
Requires-Dist: js2py
Requires-Dist: typing-extensions
Requires-Dist: PyExecJS
Requires-Dist: duckduckgo-search
Requires-Dist: nest-asyncio
Requires-Dist: waitress
Requires-Dist: werkzeug
Requires-Dist: loguru
Requires-Dist: pillow
Requires-Dist: platformdirs
Requires-Dist: numpy
Requires-Dist: asgiref
Requires-Dist: fastapi
Requires-Dist: uvicorn
Requires-Dist: flask
Requires-Dist: py-arkose-generator
Requires-Dist: asyncstdlib
Requires-Dist: async-property
Requires-Dist: undetected-chromedriver
Requires-Dist: bs4
